setup.cfg
setup.py
macrox.egg-info/PKG-INFO
macrox.egg-info/SOURCES.txt
macrox.egg-info/dependency_links.txt
macrox.egg-info/entry_points.txt
macrox.egg-info/requires.txt
macrox.egg-info/top_level.txt
src/client.py
src/globals.py
src/interpreter.py
src/parser.py
src/tokenizer.py
src/commands/base_command.py
src/nodes/__init__.py
src/nodes/assign.py
src/nodes/bases.py
src/nodes/binops.py
src/nodes/break_.py
src/nodes/call.py
src/nodes/clear_interrupt.py
src/nodes/exit_.py
src/nodes/if_.py
src/nodes/import_.py
src/nodes/interrupt.py
src/nodes/jump.py
src/nodes/label.py
src/nodes/logops.py
src/nodes/replay.py
src/nodes/return_.py
src/nodes/root.py
src/nodes/sleep.py
src/nodes/while_.py
src/tokens/base_token.py
src/utils/debugger.py
src/utils/dualstack.py
src/utils/global_argument_handler.py
src/utils/importer.py
src/utils/interrupt_manager.py
src/utils/interrupt_queue.py
src/utils/jump_handler.py
src/utils/logger.py
src/utils/options.py
src/utils/prettyprint.py
src/utils/recorder.py
src/utils/terminate.py
src/utils/variable_handler.py